Workbook

Sheet Passo a passo
A1: AIDA Documents — guia de coleta
A2: Ordem pensada para começar pelo que é mais difícil de conseguir (os reais) e gerar os de IA imitando os mesmos programas.
A3: Meta: ferramenta CONFIÁVEL no site (~2.700 PDFs). Três fases, cada uma usa o que a anterior coletou: TCC (400) → site beta com selo 'em validação' (1.400) → site confiável (2.700). Ver aba Metas.
A5: Etapa | B5: O quê | C5: Como fazer
A6: 0 | B6: Preparar (1 dia) | C6: 1) No Drive, crie AIDA_Documentos/treino/{reais, ia, manipulados} e AIDA_Documentos/teste/{reais, ia, manipulados}. 2) Nome de cada arquivo: <ID>-<CLASSE>-<caso>.pdf, ex.: 0008-REAL-c1.pdf (o ID aparece sozinho na aba Coleta). 3) A pasta é decidida pela coluna 'Conjunto' (treino ou teste). Arquivos de teste NÃO são abertos nem usados até a avaliação final. 4) Nunca edite, tarje ou 'limpe' um PDF real: isso cria marcas de edição e ele vira um falso MANIPULADO. 5) PDFs com dados pessoais ficam só no Drive privado da equipe, nunca no GitHub.
A7: 1 | B7: Reais de sistema — Caso 1 (TCC 150 · site 1.000) | C7: O gargalo. Comece por aqui. • Seus próprios: boletos, faturas (luz, água, celular, internet), extratos, comprovantes PIX, NF-e de compras online, holerites. Baixe direto do app/site do emissor. • De colegas/família: só com autorização por escrito (marque 'Autorização por escrito'; se ainda não tem, 'PENDENTE'). • Públicos: editais, diários oficiais, notas e contratos do Portal da Transparência, atas e certidões de prefeituras. • Varie os emissores: pelo menos 10 no TCC e 30 para o site bancos/empresas/órgãos diferentes. Anote o emissor em 'Origem / fonte'.
A8: 2 | B8: Reais de texto — Caso 2 (TCC 50 · site 500) | C8: Documentos escritos por pessoas, DO MESMO TIPO dos que a IA vai gerar: provas, listas de exercício, redações, trabalhos, relatórios. • Peça a professores e colegas da Etec PDFs feitos em 2025–2026 (Word, Google Docs, LibreOffice, Canva). • Prefira textos feitos ANTES do uso de IA ou com declaração do autor de que não usou IA. • Os reais antigos (2017–2018) servem, mas não podem ser maioria: a data vira atalho.
A9: 3 | B9: IA montando o PDF — Caso 1 (TCC 100 · site 350) | C9: Peça à IA o documento JÁ em PDF (use os prompts da aba 'Prompts IA'). • ChatGPT (análise de dados), Claude, Gemini: eles escrevem código Python e devolvem o PDF (ReportLab/FPDF). • Peça também em HTML e salve pelo navegador em PDF (Ctrl+P > Salvar como PDF). • Varie: tipo de documento, IA, programa. Nenhum programa com mais de 30% (veja a aba Variedade).
A10: 4 | B10: IA colada e exportada — Caso 2 (TCC 50 · site 500) | C10: O caso difícil. • Peça à IA só o TEXTO (prova, redação, relatório, contrato...). Copie e cole no Word, Google Docs, LibreOffice ou Canva e exporte em PDF. • Use os MESMOS programas dos reais da etapa 2 (se os reais têm Word e Docs, os de IA também têm). • Em ~1/3 deles, edite o texto à mão antes de exportar (troque palavras, corte frases): é o que um usuário real faria.
A11: 5 | B11: Manipulados — Caso 1 (TCC 50 · site 350) | C11: Use CÓPIAS de reais seus (etapa 1). O original real continua na pasta reais; a cópia editada vai para manipulados. • Mude valor, data, nome ou CNPJ em: iLovePDF, Sejda, Smallpdf, Foxit, Adobe Acrobat, Canva. • Também: print da tela > editar no Photoshop/celular > salvar como PDF. • Anote em Observações o que foi mudado (ex.: 'valor 150,00 -> 1.500,00').
A12: 6 | B12: Registrar (sempre) | C12: Registre cada arquivo na aba Coleta NA HORA em que salvar no Drive. Preencha tudo; o Programa sai em Adobe Reader > Arquivo > Propriedades > 'Produtor do PDF'. Uma vez por semana, olhe as abas Metas e Variedade: qualquer 'atenção' em vermelho diz o que coletar a seguir.
A13: 7 | B13: Pontos de controle | C13: • Com 30 por classe: rode python -m aida_documents.treinar AIDA_Documentos/treino --saida estudo e veja quais características separam e quais são atalho. • Com 100 por classe: rode de novo; ajuste pesos e características usando SÓ a pasta treino. • Ao bater a meta: rode UMA VEZ na pasta teste. Esse é o número que vai para o TCC (acerto, falso positivo, IA detectada, % inconclusivo). • Se mexer no modelo depois de ver o teste, o teste deixa de valer: colete um teste novo.
A14: 8 | B14: Fases até o site | C14: • FASE 1 — TCC (400): etapas 1 a 7. Resultado vai para o TCC, não para o site. • FASE 2 — Site beta (1.400): só o Caso 1 decide (IA/MANIPULADA). O site mostra 'em validação' e o falso positivo medido (< 2%). O Caso 2 aparece só como indício fraco. • FASE 3 — Site confiável (2.700): 300 reais no teste do Caso 1 sem nenhum falso positivo => publicar 'falso positivo < 1%'. Se houver 1 ou mais erros, corrigir e coletar um teste NOVO. • O Caso 2 (texto colado) NUNCA decide sozinho no site, mesmo na fase 3: no máximo vira 'suspeita' e o resultado fica INCONCLUSIVO.
A15: 9 | B15: Depois de publicar | C15: • A cada IA nova (ex.: GPT novo, Gemini novo): gerar 30 documentos com ela e testar. Se a detecção cair, ela entra no treino. • A cada 6 meses: coletar 100 reais novos e conferir o falso positivo de novo (bancos e sistemas mudam o PDF). • No site, pedir ao usuário consentimento para usar o arquivo e o rótulo dele (LGPD) e revisar à mão os casos contestados.
A17: Legenda
B18: Branco | C18: Coleta: preencha (as colunas com lista têm seta de escolha).
B19: Cinza | C19: Coleta: automático (ID e Conjunto). Não edite.
B20: Amarelo/azul | C20: Metas: valores de meta que você pode mudar.
B21: Vermelho | C21: Algo pede atenção: autorização pendente, programa acima de 30%, checagem falhando.
B22: Azul claro | C22: Coleta: arquivo sorteado para 'teste'. Vai para a pasta teste/.
B24: As 7 primeiras linhas da Coleta são o lote de 08/10 (pasta DOCS GATO) e servem de exemplo de preenchimento.

Sheet Coleta
A1: ID | B1: Arquivo | C1: Classe | D1: Caso | E1: Tipo de documento | F1: Assunto / descrição curta | G1: Programa que gerou o PDF | H1: IA usada | I1: Ano do documento | J1: Origem / fonte | K1: Tem dados pessoais? | L1: Autorização | M1: Conjunto (automático) | N1: Pasta no Drive | O1: Coletado por | P1: Data da coleta | Q1: Observações
A2: =IF(B2="","",ROW()-1) -> 1 | B2: Documento-IA.pdf | C2: IA | D2: 1 - Estrutura (PDF feito/editado) | E2: Prova/atividade escolar | F2: Prova de literatura 'A Cartomante' (Etec), 3 págs. | G2: ReportLab (Python) | H2: Não informado | I2: 2026 | J2: Gerado para o TCC | K2: Não | L2: Gerado para o TCC | M2: =IF(OR(C2="",D2=""),"",IF(MOD(COUNTIFS($C$2:C2,C2,$D$2:D2,D2)*7,10)<3,"teste","treino")) -> treino | N2: DOCS GATO | O2: Equipe | P2: 08/10/2026 | Q2: Regravado pelo pypdf (apagou o Producer). Lote de 08/10.
A3: =IF(B3="","",ROW()-1) -> 2 | B3: Documento-IA2.pdf | C3: IA | D3: 1 - Estrutura (PDF feito/editado) | E3: Orçamento | F3: Orçamento fictício 'Nexora' nº 2026/0147 | G3: ReportLab (Python) | H3: Não informado | I3: 2026 | J3: Gerado para o TCC | K3: Não | L3: Gerado para o TCC | M3: =IF(OR(C3="",D3=""),"",IF(MOD(COUNTIFS($C$2:C3,C3,$D$2:D3,D3)*7,10)<3,"teste","treino")) -> treino | N3: DOCS GATO | O3: Equipe | P3: 08/10/2026 | Q3: CNPJ/CPF inventados com dígito certo. Lote de 08/10.
A4: =IF(B4="","",ROW()-1) -> 3 | B4: Documento-IA3.pdf | C4: IA | D4: 1 - Estrutura (PDF feito/editado) | E4: Prova/atividade escolar | F4: Gabarito da prova 'A Cartomante' | G4: ReportLab (Python) | H4: Não informado | I4: 2026 | J4: Gerado para o TCC | K4: Sim | L4: Gerado para o TCC | M4: =IF(OR(C4="",D4=""),"",IF(MOD(COUNTIFS($C$2:C4,C4,$D$2:D4,D4)*7,10)<3,"teste","treino")) -> teste | N4: DOCS GATO | O4: Equipe | P4: 08/10/2026 | Q4: Tem o nome de um aluno nos metadados e no texto. Lote de 08/10.
A5: =IF(B5="","",ROW()-1) -> 4 | B5: Documento-REAL.pdf | C5: REAL | D5: 2 - Texto (IA colado e exportado) | E5: Revista/boletim | F5: Revista Fonte nº 20 (Prodemge), 9 págs. extraídas | G5: PDFsam | H5: Nenhuma (documento real) | I5: 2018 | J5: prodemge.gov.br (público) | K5: Não | L5: Público (não precisa) | M5: =IF(OR(C5="",D5=""),"",IF(MOD(COUNTIFS($C$2:C5,C5,$D$2:D5,D5)*7,10)<3,"teste","treino")) -> treino | N5: DOCS GATO | O5: Equipe | P5: 08/10/2026 | Q5: Páginas separadas no PDFsam. Lote de 08/10.
A6: =IF(B6="","",ROW()-1) -> 5 | B6: Documento-REAL2.pdf | C6: REAL | D6: 2 - Texto (IA colado e exportado) | E6: Artigo/relatório | F6: Artigo 'Agronegócio Digital 4.0' (A. Cereda Jr.) | G6: Microsoft Word | H6: Nenhuma (documento real) | I6: 2018 | J6: Artigo publicado (público) | K6: Não | L6: Público (não precisa) | M6: =IF(OR(C6="",D6=""),"",IF(MOD(COUNTIFS($C$2:C6,C6,$D$2:D6,D6)*7,10)<3,"teste","treino")) -> treino | N6: DOCS GATO | O6: Equipe | P6: 08/10/2026 | Q6: Lote de 08/10.
A7: =IF(B7="","",ROW()-1) -> 6 | B7: Documento-REAL3.pdf | C7: REAL | D7: 2 - Texto (IA colado e exportado) | E7: Artigo/relatório | F7: Artigo 'Mapas, aplicativos móveis e a nuvem' (A. Cereda Jr.) | G7: Microsoft Word | H7: Nenhuma (documento real) | I7: 2017 | J7: Artigo publicado (público) | K7: Não | L7: Público (não precisa) | M7: =IF(OR(C7="",D7=""),"",IF(MOD(COUNTIFS($C$2:C7,C7,$D$2:D7,D7)*7,10)<3,"teste","treino")) -> teste | N7: DOCS GATO | O7: Equipe | P7: 08/10/2026 | Q7: Lote de 08/10.
A8: =IF(B8="","",ROW()-1) -> 7 | B8: Documento-REAL4.pdf | C8: REAL | D8: 2 - Texto (IA colado e exportado) | E8: Artigo/relatório | F8: Artigo 'Gestão de Políticas Públicas e as (geo)Tecnologias' | G8: Microsoft Word | H8: Nenhuma (documento real) | I8: 2017 | J8: Artigo publicado (público) | K8: Não | L8: Público (não precisa) | M8: =IF(OR(C8="",D8=""),"",IF(MOD(COUNTIFS($C$2:C8,C8,$D$2:D8,D8)*7,10)<3,"teste","treino")) -> treino | N8: DOCS GATO | O8: Equipe | P8: 08/10/2026 | Q8: Lote de 08/10.
A9: =IF(B9="","",ROW()-1) | M9: =IF(OR(C9="",D9=""),"",IF(MOD(COUNTIFS($C$2:C9,C9,$D$2:D9,D9)*7,10)<3,"teste","treino"))
A10: =IF(B10="","",ROW()-1) | M10: =IF(OR(C10="",D10=""),"",IF(MOD(COUNTIFS($C$2:C10,C10,$D$2:D10,D10)*7,10)<3,"teste","treino"))
A11: =IF(B11="","",ROW()-1) | M11: =IF(OR(C11="",D11=""),"",IF(MOD(COUNTIFS($C$2:C11,C11,$D$2:D11,D11)*7,10)<3,"teste","treino"))
A12: =IF(B12="","",ROW()-1) | M12: =IF(OR(C12="",D12=""),"",IF(MOD(COUNTIFS($C$2:C12,C12,$D$2:D12,D12)*7,10)<3,"teste","treino"))
A13: =IF(B13="","",ROW()-1) | M13: =IF(OR(C13="",D13=""),"",IF(MOD(COUNTIFS($C$2:C13,C13,$D$2:D13,D13)*7,10)<3,"teste","treino"))
A14: =IF(B14="","",ROW()-1) | M14: =IF(OR(C14="",D14=""),"",IF(MOD(COUNTIFS($C$2:C14,C14,$D$2:D14,D14)*7,10)<3,"teste","treino"))
A15: =IF(B15="","",ROW()-1) | M15: =IF(OR(C15="",D15=""),"",IF(MOD(COUNTIFS($C$2:C15,C15,$D$2:D15,D15)*7,10)<3,"teste","treino"))
A16: =IF(B16="","",ROW()-1) | M16: =IF(OR(C16="",D16=""),"",IF(MOD(COUNTIFS($C$2:C16,C16,$D$2:D16,D16)*7,10)<3,"teste","treino"))
A17: =IF(B17="","",ROW()-1) | M17: =IF(OR(C17="",D17=""),"",IF(MOD(COUNTIFS($C$2:C17,C17,$D$2:D17,D17)*7,10)<3,"teste","treino"))
A18: =IF(B18="","",ROW()-1) | M18: =IF(OR(C18="",D18=""),"",IF(MOD(COUNTIFS($C$2:C18,C18,$D$2:D18,D18)*7,10)<3,"teste","treino"))
A19: =IF(B19="","",ROW()-1) | M19: =IF(OR(C19="",D19=""),"",IF(MOD(COUNTIFS($C$2:C19,C19,$D$2:D19,D19)*7,10)<3,"teste","treino"))
A20: =IF(B20="","",ROW()-1) | M20: =IF(OR(C20="",D20=""),"",IF(MOD(COUNTIFS($C$2:C20,C20,$D$2:D20,D20)*7,10)<3,"teste","treino"))
... A3001: =IF(B3001="","",ROW()-1) | M3001: =IF(OR(C3001="",D3001=""),"",IF(MOD(COUNTIFS($C$2:C3001,C3001,$D$2:D3001,D3001)*7,10)<3,"teste","treino"))

Sheet Metas
A1: Metas da coleta
A2: Tudo nesta aba é calculado a partir da aba Coleta. Só as colunas de meta (amarelas) podem ser mudadas.
A4: Caso | B4: Classe | C4: Coletados | D4: dos quais 'teste' | E4: Meta TCC | F4: Meta site beta | G4: Meta site CONFIÁVEL | H4: Progresso rumo ao site | I4: Faltam p/ site | J4: Hoje dá para afirmar*
A5: 1 - Estrutura (PDF feito/editado) | B5: REAL | C5: =COUNTIFS(Coleta!$D$2:$D$3001,A5,Coleta!$C$2:$C$3001,B5) -> 0 | D5: =COUNTIFS(Coleta!$D$2:$D$3001,A5,Coleta!$C$2:$C$3001,B5,Coleta!$M$2:$M$3001,"teste") -> 0 | E5: 150 | F5: 500 | G5: 1000 | H5: =IF(G5=0,0,MIN(1,C5/G5)) -> 0 | I5: =MAX(0,G5-C5) -> 1000 | J5: =IF(D5=0,"-",MIN(1,3/D5)) -> -
A6: 1 - Estrutura (PDF feito/editado) | B6: IA | C6: =COUNTIFS(Coleta!$D$2:$D$3001,A6,Coleta!$C$2:$C$3001,B6) -> 3 | D6: =COUNTIFS(Coleta!$D$2:$D$3001,A6,Coleta!$C$2:$C$3001,B6,Coleta!$M$2:$M$3001,"teste") -> 1 | E6: 100 | F6: 250 | G6: 350 | H6: =IF(G6=0,0,MIN(1,C6/G6)) -> 0.0085714286 | I6: =MAX(0,G6-C6) -> 347 | J6: =IF(D6=0,"-",MIN(1,1.96*SQRT(0.09/D6))) -> 0.588
A7: 1 - Estrutura (PDF feito/editado) | B7: MANIPULADO | C7: =COUNTIFS(Coleta!$D$2:$D$3001,A7,Coleta!$C$2:$C$3001,B7) -> 0 | D7: =COUNTIFS(Coleta!$D$2:$D$3001,A7,Coleta!$C$2:$C$3001,B7,Coleta!$M$2:$M$3001,"teste") -> 0 | E7: 50 | F7: 250 | G7: 350 | H7: =IF(G7=0,0,MIN(1,C7/G7)) -> 0 | I7: =MAX(0,G7-C7) -> 350 | J7: =IF(D7=0,"-",MIN(1,1.96*SQRT(0.09/D7))) -> -
A8: 2 - Texto (IA colado e exportado) | B8: REAL | C8: =COUNTIFS(Coleta!$D$2:$D$3001,A8,Coleta!$C$2:$C$3001,B8) -> 4 | D8: =COUNTIFS(Coleta!$D$2:$D$3001,A8,Coleta!$C$2:$C$3001,B8,Coleta!$M$2:$M$3001,"teste") -> 1 | E8: 50 | F8: 200 | G8: 500 | H8: =IF(G8=0,0,MIN(1,C8/G8)) -> 0.008 | I8: =MAX(0,G8-C8) -> 496 | J8: =IF(D8=0,"-",MIN(1,3/D8)) -> 1
A9: 2 - Texto (IA colado e exportado) | B9: IA | C9: =COUNTIFS(Coleta!$D$2:$D$3001,A9,Coleta!$C$2:$C$3001,B9) -> 0 | D9: =COUNTIFS(Coleta!$D$2:$D$3001,A9,Coleta!$C$2:$C$3001,B9,Coleta!$M$2:$M$3001,"teste") -> 0 | E9: 50 | F9: 200 | G9: 500 | H9: =IF(G9=0,0,MIN(1,C9/G9)) -> 0 | I9: =MAX(0,G9-C9) -> 500 | J9: =IF(D9=0,"-",MIN(1,1.96*SQRT(0.09/D9))) -> -
A10: TOTAL | C10: =SUM(C5:C9) -> 7 | D10: =SUM(D5:D9) -> 2 | E10: =SUM(E5:E9) -> 400 | F10: =SUM(F5:F9) -> 1400 | G10: =SUM(G5:G9) -> 2700 | H10: =IF(G10=0,0,MIN(1,C10/G10)) -> 0.0025925926 | I10: =SUM(I5:I9) -> 2693
A11: * REAL: com zero erros nos reais do teste, o falso positivo fica ABAIXO desse valor (regra do 3: 3 ÷ reais no teste).
A12: * IA/MANIPULADO: margem (±) da taxa de detecção medida no teste, supondo ~90% de acerto.
A13: Site CONFIÁVEL: 300 reais no teste do Caso 1 (falso positivo < 1%) e 150 no Caso 2 (< 2%). Site beta: < 2% e < 5%, com selo 'em validação'.
A14: O teste é ~30% do total: por isso 1.000 reais no total para ter 300 no teste.
A16: Checagens de qualidade
A17: Checagem | B17: Valor | C17: Alvo | D17: OK?
A18: Reais de 2025–2026 (% dos reais) | B18: =IFERROR((COUNTIFS(Coleta!$C$2:$C$3001,"REAL",Coleta!$I$2:$I$3001,">=2025"))/COUNTIF(Coleta!$C$2:$C$3001,"REAL"),0) -> 0 | C18: 0.5 | D18: =IF(B18>=C18,"OK","atenção") -> atenção
A19: Programas diferentes entre os REAIS | B19: =Variedade!C25 -> 2 | C19: 4 | D19: =IF(B19>=C19,"OK","atenção") -> atenção
A20: Programas diferentes entre os IA | B20: =Variedade!E25 -> 1 | C20: 4 | D20: =IF(B20>=C20,"OK","atenção") -> atenção
A21: Programas diferentes entre os MANIPULADOS | B21: =Variedade!G25 -> 0 | C21: 4 | D21: =IF(B21>=C21,"OK","atenção") -> atenção
A22: Maior fatia de um programa (REAL) | B22: =Variedade!C26 -> 0.75 | C22: 0.3 | D22: =IF(B22<=C22,"OK","atenção") -> atenção
A23: Maior fatia de um programa (IA) | B23: =Variedade!E26 -> 1 | C23: 0.3 | D23: =IF(B23<=C23,"OK","atenção") -> atenção
A24: Reais no teste — Caso 1 (para FP < 1%) | B24: =D5 -> 0 | C24: 300 | D24: =IF(B24>=C24,"OK","atenção") -> atenção
A25: Reais no teste — Caso 2 (para FP < 2%) | B25: =D8 -> 1 | C25: 150 | D25: =IF(B25>=C25,"OK","atenção") -> atenção
A26: Autorizações PENDENTES | B26: =COUNTIF(Coleta!$L$2:$L$3001,"PENDENTE") -> 0 | C26: 0 | D26: =IF(B26<=C26,"OK","atenção") -> OK
A27: Arquivos sem Programa preenchido | B27: =COUNTIFS(Coleta!$B$2:$B$3001,"<>",Coleta!$G$2:$G$3001,"") -> 0 | C27: 0 | D27: =IF(B27<=C27,"OK","atenção") -> OK

Sheet Variedade
A1: Variedade de programas por classe
A2: Regra: nenhum programa com mais de 30% de uma classe, e os mesmos programas nas duas classes. Calculado; não edite.
A3: Programa | C3: REAL | D3: % REAL | E3: IA | F3: % IA | G3: MANIPULADO | H3: % MANIP.
A4: Sistema emissor (banco, SEFAZ, prefeitura) | C4: =COUNTIFS(Coleta!$G$2:$G$3001,$A4,Coleta!$C$2:$C$3001,"REAL") -> 0 | D4: =IF(COUNTIF(Coleta!$C$2:$C$3001,"REAL")=0,0,C4/COUNTIF(Coleta!$C$2:$C$3001,"REAL")) -> 0 | E4: =COUNTIFS(Coleta!$G$2:$G$3001,$A4,Coleta!$C$2:$C$3001,"IA") -> 0 | F4: =IF(COUNTIF(Coleta!$C$2:$C$3001,"IA")=0,0,E4/COUNTIF(Coleta!$C$2:$C$3001,"IA")) -> 0 | G4: =COUNTIFS(Coleta!$G$2:$G$3001,$A4,Coleta!$C$2:$C$3001,"MANIPULADO") -> 0 | H4: =IF(COUNTIF(Coleta!$C$2:$C$3001,"MANIPULADO")=0,0,G4/COUNTIF(Coleta!$C$2:$C$3001,"MANIPULADO")) -> 0
A5: Microsoft Word | C5: =COUNTIFS(Coleta!$G$2:$G$3001,$A5,Coleta!$C$2:$C$3001,"REAL") -> 3 | D5: =IF(COUNTIF(Coleta!$C$2:$C$3001,"REAL")=0,0,C5/COUNTIF(Coleta!$C$2:$C$3001,"REAL")) -> 0.75 | E5: =COUNTIFS(Coleta!$G$2:$G$3001,$A5,Coleta!$C$2:$C$3001,"IA") -> 0 | F5: =IF(COUNTIF(Coleta!$C$2:$C$3001,"IA")=0,0,E5/COUNTIF(Coleta!$C$2:$C$3001,"IA")) -> 0 | G5: =COUNTIFS(Coleta!$G$2:$G$3001,$A5,Coleta!$C$2:$C$3001,"MANIPULADO") -> 0 | H5: =IF(COUNTIF(Coleta!$C$2:$C$3001,"MANIPULADO")=0,0,G5/COUNTIF(Coleta!$C$2:$C$3001,"MANIPULADO")) -> 0
A6: Google Docs | C6: =COUNTIFS(Coleta!$G$2:$G$3001,$A6,Coleta!$C$2:$C$3001,"REAL") -> 0 | D6: =IF(COUNTIF(Coleta!$C$2:$C$3001,"REAL")=0,0,C6/COUNTIF(Coleta!$C$2:$C$3001,"REAL")) -> 0 | E6: =COUNTIFS(Coleta!$G$2:$G$3001,$A6,Coleta!$C$2:$C$3001,"IA") -> 0 | F6: =IF(COUNTIF(Coleta!$C$2:$C$3001,"IA")=0,0,E6/COUNTIF(Coleta!$C$2:$C$3001,"IA")) -> 0 | G6: =COUNTIFS(Coleta!$G$2:$G$3001,$A6,Coleta!$C$2:$C$3001,"MANIPULADO") -> 0 | H6: =IF(COUNTIF(Coleta!$C$2:$C$3001,"MANIPULADO")=0,0,G6/COUNTIF(Coleta!$C$2:$C$3001,"MANIPULADO")) -> 0
A7: LibreOffice | C7: =COUNTIFS(Coleta!$G$2:$G$3001,$A7,Coleta!$C$2:$C$3001,"REAL") -> 0 | D7: =IF(COUNTIF(Coleta!$C$2:$C$3001,"REAL")=0,0,C7/COUNTIF(Coleta!$C$2:$C$3001,"REAL")) -> 0 | E7: =COUNTIFS(Coleta!$G$2:$G$3001,$A7,Coleta!$C$2:$C$3001,"IA") -> 0 | F7: =IF(COUNTIF(Coleta!$C$2:$C$3001,"IA")=0,0,E7/COUNTIF(Coleta!$C$2:$C$3001,"IA")) -> 0 | G7: =COUNTIFS(Coleta!$G$2:$G$3001,$A7,Coleta!$C$2:$C$3001,"MANIPULADO") -> 0 | H7: =IF(COUNTIF(Coleta!$C$2:$C$3001,"MANIPULADO")=0,0,G7/COUNTIF(Coleta!$C$2:$C$3001,"MANIPULADO")) -> 0
A8: Canva | C8: =COUNTIFS(Coleta!$G$2:$G$3001,$A8,Coleta!$C$2:$C$3001,"REAL") -> 0 | D8: =IF(COUNTIF(Coleta!$C$2:$C$3001,"REAL")=0,0,C8/COUNTIF(Coleta!$C$2:$C$3001,"REAL")) -> 0 | E8: =COUNTIFS(Coleta!$G$2:$G$3001,$A8,Coleta!$C$2:$C$3001,"IA") -> 0 | F8: =IF(COUNTIF(Coleta!$C$2:$C$3001,"IA")=0,0,E8/COUNTIF(Coleta!$C$2:$C$3001,"IA")) -> 0 | G8: =COUNTIFS(Coleta!$G$2:$G$3001,$A8,Coleta!$C$2:$C$3001,"MANIPULADO") -> 0 | H8: =IF(COUNTIF(Coleta!$C$2:$C$3001,"MANIPULADO")=0,0,G8/COUNTIF(Coleta!$C$2:$C$3001,"MANIPULADO")) -> 0
A9: Navegador (Chrome/Edge - imprimir PDF) | C9: =COUNTIFS(Coleta!$G$2:$G$3001,$A9,Coleta!$C$2:$C$3001,"REAL") -> 0 | D9: =IF(COUNTIF(Coleta!$C$2:$C$3001,"REAL")=0,0,C9/COUNTIF(Coleta!$C$2:$C$3001,"REAL")) -> 0 | E9: =COUNTIFS(Coleta!$G$2:$G$3001,$A9,Coleta!$C$2:$C$3001,"IA") -> 0 | F9: =IF(COUNTIF(Coleta!$C$2:$C$3001,"IA")=0,0,E9/COUNTIF(Coleta!$C$2:$C$3001,"IA")) -> 0 | G9: =COUNTIFS(Coleta!$G$2:$G$3001,$A9,Coleta!$C$2:$C$3001,"MANIPULADO") -> 0 | H9: =IF(COUNTIF(Coleta!$C$2:$C$3001,"MANIPULADO")=0,0,G9/COUNTIF(Coleta!$C$2:$C$3001,"MANIPULADO")) -> 0
A10: Adobe Acrobat | C10: =COUNTIFS(Coleta!$G$2:$G$3001,$A10,Coleta!$C$2:$C$3001,"REAL") -> 0 | D10: =IF(COUNTIF(Coleta!$C$2:$C$3001,"REAL")=0,0,C10/COUNTIF(Coleta!$C$2:$C$3001,"REAL")) -> 0 | E10: =COUNTIFS(Coleta!$G$2:$G$3001,$A10,Coleta!$C$2:$C$3001,"IA") -> 0 | F10: =IF(COUNTIF(Coleta!$C$2:$C$3001,"IA")=0,0,E10/COUNTIF(Coleta!$C$2:$C$3001,"IA")) -> 0 | G10: =COUNTIFS(Coleta!$G$2:$G$3001,$A10,Coleta!$C$2:$C$3001,"MANIPULADO") -> 0 | H10: =IF(COUNTIF(Coleta!$C$2:$C$3001,"MANIPULADO")=0,0,G10/COUNTIF(Coleta!$C$2:$C$3001,"MANIPULADO")) -> 0
A11: ReportLab (Python) | C11: =COUNTIFS(Coleta!$G$2:$G$3001,$A11,Coleta!$C$2:$C$3001,"REAL") -> 0 | D11: =IF(COUNTIF(Coleta!$C$2:$C$3001,"REAL")=0,0,C11/COUNTIF(Coleta!$C$2:$C$3001,"REAL")) -> 0 | E11: =COUNTIFS(Coleta!$G$2:$G$3001,$A11,Coleta!$C$2:$C$3001,"IA") -> 3 | F11: =IF(COUNTIF(Coleta!$C$2:$C$3001,"IA")=0,0,E11/COUNTIF(Coleta!$C$2:$C$3001,"IA")) -> 1 | G11: =COUNTIFS(Coleta!$G$2:$G$3001,$A11,Coleta!$C$2:$C$3001,"MANIPULADO") -> 0 | H11: =IF(COUNTIF(Coleta!$C$2:$C$3001,"MANIPULADO")=0,0,G11/COUNTIF(Coleta!$C$2:$C$3001,"MANIPULADO")) -> 0
A12: FPDF (Python) | C12: =COUNTIFS(Coleta!$G$2:$G$3001,$A12,Coleta!$C$2:$C$3001,"REAL") -> 0 | D12: =IF(COUNTIF(Coleta!$C$2:$C$3001,"REAL")=0,0,C12/COUNTIF(Coleta!$C$2:$C$3001,"REAL")) -> 0 | E12: =COUNTIFS(Coleta!$G$2:$G$3001,$A12,Coleta!$C$2:$C$3001,"IA") -> 0 | F12: =IF(COUNTIF(Coleta!$C$2:$C$3001,"IA")=0,0,E12/COUNTIF(Coleta!$C$2:$C$3001,"IA")) -> 0 | G12: =COUNTIFS(Coleta!$G$2:$G$3001,$A12,Coleta!$C$2:$C$3001,"MANIPULADO") -> 0 | H12: =IF(COUNTIF(Coleta!$C$2:$C$3001,"MANIPULADO")=0,0,G12/COUNTIF(Coleta!$C$2:$C$3001,"MANIPULADO")) -> 0
A13: jsPDF (JavaScript) | C13: =COUNTIFS(Coleta!$G$2:$G$3001,$A13,Coleta!$C$2:$C$3001,"REAL") -> 0 | D13: =IF(COUNTIF(Coleta!$C$2:$C$3001,"REAL")=0,0,C13/COUNTIF(Coleta!$C$2:$C$3001,"REAL")) -> 0 | E13: =COUNTIFS(Coleta!$G$2:$G$3001,$A13,Coleta!$C$2:$C$3001,"IA") -> 0 | F13: =IF(COUNTIF(Coleta!$C$2:$C$3001,"IA")=0,0,E13/COUNTIF(Coleta!$C$2:$C$3001,"IA")) -> 0 | G13: =COUNTIFS(Coleta!$G$2:$G$3001,$A13,Coleta!$C$2:$C$3001,"MANIPULADO") -> 0 | H13: =IF(COUNTIF(Coleta!$C$2:$C$3001,"MANIPULADO")=0,0,G13/COUNTIF(Coleta!$C$2:$C$3001,"MANIPULADO")) -> 0
A14: Outra biblioteca de programação | C14: =COUNTIFS(Coleta!$G$2:$G$3001,$A14,Coleta!$C$2:$C$3001,"REAL") -> 0 | D14: =IF(COUNTIF(Coleta!$C$2:$C$3001,"REAL")=0,0,C14/COUNTIF(Coleta!$C$2:$C$3001,"REAL")) -> 0 | E14: =COUNTIFS(Coleta!$G$2:$G$3001,$A14,Coleta!$C$2:$C$3001,"IA") -> 0 | F14: =IF(COUNTIF(Coleta!$C$2:$C$3001,"IA")=0,0,E14/COUNTIF(Coleta!$C$2:$C$3001,"IA")) -> 0 | G14: =COUNTIFS(Coleta!$G$2:$G$3001,$A14,Coleta!$C$2:$C$3001,"MANIPULADO") -> 0 | H14: =IF(COUNTIF(Coleta!$C$2:$C$3001,"MANIPULADO")=0,0,G14/COUNTIF(Coleta!$C$2:$C$3001,"MANIPULADO")) -> 0
A15: iLovePDF | C15: =COUNTIFS(Coleta!$G$2:$G$3001,$A15,Coleta!$C$2:$C$3001,"REAL") -> 0 | D15: =IF(COUNTIF(Coleta!$C$2:$C$3001,"REAL")=0,0,C15/COUNTIF(Coleta!$C$2:$C$3001,"REAL")) -> 0 | E15: =COUNTIFS(Coleta!$G$2:$G$3001,$A15,Coleta!$C$2:$C$3001,"IA") -> 0 | F15: =IF(COUNTIF(Coleta!$C$2:$C$3001,"IA")=0,0,E15/COUNTIF(Coleta!$C$2:$C$3001,"IA")) -> 0 | G15: =COUNTIFS(Coleta!$G$2:$G$3001,$A15,Coleta!$C$2:$C$3001,"MANIPULADO") -> 0 | H15: =IF(COUNTIF(Coleta!$C$2:$C$3001,"MANIPULADO")=0,0,G15/COUNTIF(Coleta!$C$2:$C$3001,"MANIPULADO")) -> 0
... A23: Outro | C23: =COUNTIFS(Coleta!$G$2:$G$3001,$A23,Coleta!$C$2:$C$3001,"REAL") -> 0 | D23: =IF(COUNTIF(Coleta!$C$2:$C$3001,"REAL")=0,0,C23/COUNTIF(Coleta!$C$2:$C$3001,"REAL")) -> 0 | E23: =COUNTIFS(Coleta!$G$2:$G$3001,$A23,Coleta!$C$2:$C$3001,"IA") -> 0 | F23: =IF(COUNTIF(Coleta!$C$2:$C$3001,"IA")=0,0,E23/COUNTIF(Coleta!$C$2:$C$3001,"IA")) -> 0 | G23: =COUNTIFS(Coleta!$G$2:$G$3001,$A23,Coleta!$C$2:$C$3001,"MANIPULADO") -> 0 | H23: =IF(COUNTIF(Coleta!$C$2:$C$3001,"MANIPULADO")=0,0,G23/COUNTIF(Coleta!$C$2:$C$3001,"MANIPULADO")) -> 0
A25: Programas diferentes usados | C25: =COUNTIF(C4:C23,">0") -> 2 | E25: =COUNTIF(E4:E23,">0") -> 1 | G25: =COUNTIF(G4:G23,">0") -> 0
A26: Maior fatia de um só programa | C26: =MAX(D4:D23) -> 0.75 | E26: =MAX(F4:F23) -> 1 | G26: =MAX(H4:H23) -> 0

Sheet Prompts IA
A1: Prompts para gerar os documentos de IA
A2: Troque os [colchetes] a cada uso: empresa, cidade, valores, datas, assunto. Documentos repetidos não ensinam nada ao modelo.
A4: Caso | B4: Tipo | C4: Prompt
A5: 1 | B5: Recibo | C5: Gere um PDF de recibo de prestação de serviço de [pintura residencial] em [Belo Horizonte], valor [R$ 1.850,00], datado de [12/08/2026], com dados fictícios do prestador e do cliente. Me devolva o arquivo PDF.
A6: 1 | B6: Nota fiscal | C6: Crie em PDF uma nota fiscal de serviço (NFS-e) fictícia de [consultoria em TI] para a empresa [nome], com CNPJ, itens, impostos e total. Devolva o PDF pronto para baixar.
A7: 1 | B7: Comprovante PIX | C7: Faça um comprovante de transferência PIX em PDF, no estilo de app de banco, de [R$ 320,00] para [nome], em [data e hora]. Gere o arquivo PDF.
A8: 1 | B8: Boleto | C8: Gere um boleto bancário fictício em PDF de [mensalidade escolar], vencimento [10/11/2026], valor [R$ 780,00], com linha digitável e código de barras.
A9: 1 | B9: Extrato | C9: Crie um extrato bancário em PDF de [outubro/2026] com [25] lançamentos variados (PIX, débito, salário, boletos) e saldo final. Devolva em PDF.
A10: 1 | B10: Atestado | C10: Gere um atestado médico fictício em PDF de [2 dias] de afastamento, com CRM, carimbo e assinatura simulados.
A11: 1 | B11: Via HTML | C11: Escreva o HTML/CSS de um [orçamento de reforma] com tabela de itens e totais. (Depois abra no navegador e salve como PDF.)
A12: 2 | B12: Prova escolar | C12: Escreva uma prova de [história do Brasil — Era Vargas] para o [2º ano do ensino médio] com 8 questões objetivas e 2 discursivas. Só o texto.
A13: 2 | B13: Redação | C13: Escreva uma redação dissertativa-argumentativa no modelo ENEM sobre [o uso de celulares nas escolas], com cerca de 30 linhas.
A14: 2 | B14: Relatório | C14: Escreva um relatório técnico de [visita a uma estação de tratamento de água] para a disciplina de [química], com introdução, desenvolvimento e conclusão.
A15: 2 | B15: Contrato | C15: Redija um contrato de [locação de imóvel residencial] entre [partes fictícias], com cláusulas de prazo, valor e multa.
A16: 2 | B16: Trabalho escolar | C16: Escreva um trabalho escolar sobre [Machado de Assis e o Realismo] com cerca de 2 páginas, linguagem de aluno de ensino médio.
A18: Caso 2: copie o texto, cole no Word/Google Docs/LibreOffice/Canva e exporte em PDF. Varie o programa e, em ~1/3, edite à mão antes.

Sheet Listas
A1: Classe | B1: Caso | C1: Tipo | D1: Programa | E1: IA | F1: SimNao | G1: Autorizacao
A2: REAL | B2: 1 - Estrutura (PDF feito/editado) | C2: Boleto | D2: Sistema emissor (banco, SEFAZ, prefeitura) | E2: Nenhuma (documento real) | F2: Sim | G2: Público (não precisa)
A3: IA | B3: 2 - Texto (IA colado e exportado) | C3: Nota fiscal (NF-e/NFC-e/NFS-e) | D3: Microsoft Word | E3: ChatGPT | F3: Não | G3: Documento meu
A4: MANIPULADO | C4: Extrato bancário | D4: Google Docs | E4: Gemini | G4: Autorização por escrito
C5: Comprovante PIX/transferência | D5: LibreOffice | E5: Claude | G5: Gerado para o TCC
C6: Recibo | D6: Canva | E6: Copilot | G6: PENDENTE
C7: Orçamento | D7: Navegador (Chrome/Edge - imprimir PDF) | E7: Meta AI
C8: Contrato | D8: Adobe Acrobat | E8: DeepSeek
C9: Atestado/laudo | D9: ReportLab (Python) | E9: Outra
C10: Prova/atividade escolar | D10: FPDF (Python) | E10: Não informado
C11: Redação/trabalho escolar | D11: jsPDF (JavaScript)
C12: Artigo/relatório | D12: Outra biblioteca de programação
C13: Revista/boletim | D13: iLovePDF
C14: Edital/documento público | D14: Sejda
C15: Currículo | D15: Foxit
C16: Outro | D16: Smallpdf
D17: PDFsam
D18: Photoshop/editor de imagem
D19: Scanner/CamScanner
D20: Não sei
D21: Outro
